README.md
setup.py
hicloud/__init__.py
hicloud.egg-info/PKG-INFO
hicloud.egg-info/SOURCES.txt
hicloud.egg-info/dependency_links.txt
hicloud.egg-info/requires.txt
hicloud.egg-info/top_level.txt
hicloud/utils/__init__.py
hicloud/utils/collectionutil.py
hicloud/utils/commonutil.py
hicloud/utils/datetimeutil.py
hicloud/utils/httputil.py
hicloud/utils/jsonutil.py
hicloud/utils/redisutil.py
hicloud/utils/strutil.py